maskutils/MaskUtils.py
maskutils/__init__.py
maskutils-0.0.2.dist-info/DESCRIPTION.rst
maskutils-0.0.2.dist-info/METADATA
maskutils-0.0.2.dist-info/RECORD
maskutils-0.0.2.dist-info/WHEEL
maskutils-0.0.2.dist-info/metadata.json
maskutils-0.0.2.dist-info/top_level.txt
maskutils-0.0.2.dist-info/zip-safe
