Metadata-Version: 2.0
Name: maskutils
Version: 0.0.2
Summary: Functionality for working with 2D image masks
Home-page: https://github.com/adamrehn/maskutils
Author: Adam Rehn
Author-email: adam@adamrehn.com
License: MIT
Platform: UNKNOWN
Requires-Dist: numpy
Requires-Dist: opencv-python
Requires-Dist: slidingwindow
